iriusrisk/__init__.py
iriusrisk/autoinit.py
iriusrisk/commandline.py
iriusrisk/configfile.py
iriusrisk/v1/__init__.py
iriusrisk/v1/facade.py
iriusrisk_apishell_v1-0.3.4.dist-info/METADATA
iriusrisk_apishell_v1-0.3.4.dist-info/WHEEL
iriusrisk_apishell_v1-0.3.4.dist-info/RECORD
