Metadata-Version: 2.1
Name: iriusrisk_apishell_v1
Version: 0.3.4
Summary: Aids calling IriusRisk v1 APIs. Starting point when creating more complex scripts that create, call and process API calls.
Author-Email: Walter Gildersleeve <wgildersleeve@iriusrisk.com>
Classifier: Programming Language :: Python :: 3
Classifier: License :: OSI Approved :: MIT License
Classifier: Operating System :: OS Independent
Project-URL: Homepage, https://github.com/iriusrisk/IriusRisk-Central/tree/main/Integrations/ApiShell
Project-URL: Bug tracker, https://github.com/iriusrisk/IriusRisk-Central/issues
Requires-Python: >=3.7
